{"article_id": "101524", "revised_title": "Inquiries on Mines: A Natural History Approach", "topics": ["Geology", "Mining", "Mineralogy", "Natural Resources", "Environmental Science"], "tldr": "The author presents a comprehensive list of inquiries and questions to be addressed in the study of mines, their surrounding environments, and the minerals they contain. This serves as a foundation for a natural history approach to understanding the geological and environmental aspects of mining.", "scientific_discipline": "Environmental & Earth Sciences", "scientific_subdiscipline": "Geology & Mineralogy"}