{"article_id": "101627", "revised_title": "Observations on the Running of Sap in Trees and Birch Water", "topics": ["Tree Physiology", "Sap Collection", "Weather Indicators", "Birch Water", "Plant Science"], "tldr": "Dr. Ez. Tonge investigates the relationship between tree sap flow and weather conditions, comparing it to a weather glass. He also explores methods of ordering birch water and its potential uses, such as brewing ale and as a warming drink.", "scientific_discipline": "Environmental & Earth Sciences", "scientific_subdiscipline": "Plant Physiology & Ecology"}