{"article_id": "101644", "revised_title": "Reflections on April 1675 Transactions and Soil Fertility", "topics": ["Chemistry", "Agriculture", "Philosophy", "Geology", "Economics"], "tldr": "The author reflects on the recent transactions of April 1675, discussing various scientific topics such as Dr. Leibnitz's watch, Hevelius's accuracy, and Borrichius's work in chemistry. The author also shares their observations on soil fertility and the potential profit from using sea sand in Cornwall, emphasizing the importance of considering the economic impact on the community.", "scientific_discipline": "Environmental & Earth Sciences", "scientific_subdiscipline": "Soil Science & Agriculture"}