{"article_id": "102281", "revised_title": "A General Rule for Laying Mortars in Gunnery", "topics": ["Gunnery", "Mortars", "Artillery", "Elevation", "Projectile Motion"], "tldr": "The author presents a new method for calculating the elevation and charge of a mortar in gunnery, allowing for more accurate and efficient targeting of objects above or below the horizon. This method saves powder, is less dependent on precise direction, and is applicable to sea mortars.", "scientific_discipline": "Engineering & Technology", "scientific_subdiscipline": "Military & Defense Engineering"}