{"article_id": "102284", "revised_title": "Exploration and Description of Ancient Palmyra's Temple and Ruins", "topics": ["Archaeology", "Palmyra", "Ancient Architecture", "Historical Sites", "Syria"], "tldr": "The author, William Halifax, describes his journey to Palmyra, Syria, and provides a detailed account of the ancient Temple and its surrounding ruins, including the architectural features, inscriptions, and historical context of the site.", "scientific_discipline": "Social Sciences & Humanities", "scientific_subdiscipline": "Archaeology & History"}