{"article_id": "102668", "revised_title": "Discovery of Land and River Shells in Northamptonshire", "topics": ["Paleontology", "Geology", "Natural History", "Fossil Shells", "Deluge Theory"], "tldr": "The author describes the discovery of land and river shells in a bituminous marshy earth near Mears-Ashby in Northamptonshire. The shells were found buried in the earth along with vegetable matter, and the author discusses their possible origin and the implications for the study of natural history in the region.", "scientific_discipline": "Earth Sciences", "scientific_subdiscipline": "Paleontology & Stratigraphy"}