{"article_id": "103952", "revised_title": "Observations on Epidemics and Atmospheric Conditions in 18th Century Plymouth", "topics": ["Meteorology", "Epidemiology", "Atmospheric Science", "Public Health", "Medical History"], "tldr": "The author, Thomas Stack, provides a detailed account of a book that documents meteorological and medical observations made in Plymouth from 1728 to 1737. The book includes data on weather patterns, atmospheric conditions, and the prevalence of various diseases during that time period. Stack highlights the relationship between weather and disease, as well as the importance of accurate historical records for understanding public health.", "scientific_discipline": "Environmental & Earth Sciences", "scientific_subdiscipline": "Meteorology & Climatology"}