{"article_id": "104427", "revised_title": "A Description of the Island of Zetland and Its Natural Resources", "topics": ["Geography of Zetland", "Natural Resources of Zetland", "Island Ecosystems", "Seafaring and Navigation", "Local Culture and Customs"], "tldr": "The author provides a detailed account of the geography, climate, wildlife, and natural resources of the island of Zetland, including its harbors, minerals, and local customs. He also describes the island's unique features, such as the midnight sun and the Northern Lights, and praises the hospitality and virtue of its inhabitants.", "scientific_discipline": "Environmental & Earth Sciences", "scientific_subdiscipline": "Geography & Geology"}