{"article_id": "104684", "revised_title": "Aurorae Boreales Observations and Descriptions", "topics": ["Aurora Borealis", "Meteorology", "Atmospheric Phenomena", "Geophysics", "Magnetic Fields"], "tldr": "The author shares accounts of unusual aurorae borealis sightings in Norwich and Wells, England, observed on January 23, 1749. The descriptions provide details of the colors, shapes, and movements of the lights in the sky, as well as the weather conditions and magnetic needle movements during the events.", "scientific_discipline": "Environmental & Earth Sciences", "scientific_subdiscipline": "Meteorology & Atmospheric Sciences"}