{"article_id": "105064", "revised_title": "Observations on Hernias and Related Surgical Cases", "topics": ["Hernia", "Surgery", "Anatomy", "Pathology", "Urology"], "tldr": "The author presents three cases of hernias, discussing their unique characteristics and surgical treatments. The cases include a hernia with a ruptured sack, a hernia with two distinct sacks, and a complex case involving a strangulation and multiple sacks. The author also describes a natural blind duct and strictures and carnosities in the urethra.", "scientific_discipline": "Medicine & Health Sciences", "scientific_subdiscipline": "Surgery & Anatomy"}