{"article_id": "105018", "revised_title": "The Use of Bark in Treating Smallpox: A Case Study", "topics": ["Smallpox Treatment", "Bark Therapy", "Medicine & Health Sciences", "Case Study", "Infectious Diseases"], "tldr": "The author shares two case studies of smallpox patients treated with bark therapy, highlighting its effectiveness in supporting the patient's strength, preventing secondary fever, and promoting pustule maturation.", "scientific_discipline": "Medicine & Health Sciences", "scientific_subdiscipline": "Infectious Diseases & Epidemiology"}