{"article_id": "105782", "revised_title": "Anatomy of the Lymphatic System in Birds", "topics": ["Lymphatic System", "Anatomy", "Birds", "Physiology", "Absorption"], "tldr": "The author, William Hewson, investigates the lymphatic system in birds and discovers its structure and function, including the presence of two thoracic ducts and the transparent nature of the lymph. He also compares the lymphatic system in birds to that in quadrupeds and discusses the implications for absorption in birds.", "scientific_discipline": "Biology & Life Sciences", "scientific_subdiscipline": "Anatomy & Physiology"}