{"article_id": "105848", "revised_title": "Observations of the Transit of Venus and Solar Eclipse in 1769", "topics": ["Astronomy", "Transit of Venus", "Solar Eclipse", "Observational Astronomy", "Astronomical Instruments"], "tldr": "This article reports observations of the transit of Venus and the solar eclipse on June 3, 1769, made by various astronomers in Paris and other locations. The observations were conducted using different telescopes, and the data collected will help in understanding the Earth's orbit and the solar system.", "scientific_discipline": "Astronomy", "scientific_subdiscipline": "Observational Astronomy & Planetary Science"}