{"article_id": "106368", "revised_title": "An Account of the 1779 Eruption of Mount Vesuvius", "topics": ["Volcanology", "Geology", "Natural Disasters", "Mount Vesuvius", "Lava Flows"], "tldr": "The author provides a detailed account of the 1779 eruption of Mount Vesuvius, describing the lava flows, channels, and the impact on the surrounding area. He also discusses his observations of the volcano's behavior and the geological formations that resulted from the eruption.", "scientific_discipline": "Earth Sciences", "scientific_subdiscipline": "Volcanology & Geophysics"}