{"article_id": "107025", "revised_title": "Observations on the Growth and Size of Elephants", "topics": ["Elephant Growth", "Elephant Size", "Elephant Breeding", "Elephant Domestication", "Animal Husbandry"], "tldr": "The author provides detailed observations on the growth, size, and breeding of elephants, debunking myths and providing accurate data on their height and age. The study focuses on the growth of a young elephant from birth to its full size, as well as the differences in growth rates between male and female elephants.", "scientific_discipline": "Biology & Life Sciences", "scientific_subdiscipline": "Zoology & Animal Behavior"}