{"article_id": "107590", "revised_title": "The Distinctive Characteristics of Sepia and Vermes Testacea Ova", "topics": ["Reproduction and Development in Sepia and Vermes Testacea", "Comparative Anatomy", "Marine Biology", "Egg Formation and Development", "Shell Formation in Snails"], "tldr": "The author examines the distinguishing characteristics between the ova of the Sepia and Vermes Testacea, focusing on their reproductive and developmental processes. The study reveals that Sepia ova are not formed by an animal of the order Vermes Testacea, and that the Sepia uses a different method of egg formation and defense for its young.", "scientific_discipline": "Biology & Life Sciences", "scientific_subdiscipline": "Zoology & Animal Biology"}