{"article_id": "107646", "revised_title": "Anatomy and Function of the Eye and its Surrounding Muscles", "topics": ["Eye Anatomy", "Eye Movements", "Muscules and Nerves of the Orbit", "Ophthalmology", "Neurology"], "tldr": "The author examines the various motions and functions of the eye and its surrounding muscles, including the rapid, insensible motion of the eye-ball and the role of the eye-lids in protecting and clearing the eye. The article also discusses the differences in eye function during waking and sleeping states.", "scientific_discipline": "Biology & Life Sciences", "scientific_subdiscipline": "Neurobiology & Ophthalmology"}