{"article_id": "107633", "revised_title": "Corrections Applied to the Great Meridional Arc in India", "topics": ["Geodetic Surveying", "Surveying Techniques", "Geodesy", "Trigonometry", "Measurement Standards"], "tldr": "The author describes the corrections applied to the Great Meridional Arc in India, extending from latitude 8\u00b09'38\" to 18\u00b03'23\", to reduce it to the parliamentary standard. The article discusses the use of standard scales and chains in the survey and the ellipticity of the Earth, providing a table of results for different latitudes.", "scientific_discipline": "Environmental & Earth Sciences", "scientific_subdiscipline": "Geodesy & Geophysics"}