{"article_id": "108506", "revised_title": "Investigating the Thermal Effects of Fluids in Motion", "topics": ["Fluid Dynamics", "Thermal Convection", "Heat Transfer", "Porous Media", "Thermal Efficiency"], "tldr": "This article explores the thermal effects of fluids in motion, specifically focusing on the cooling effect and the role of pressure in the process. The authors conduct experiments using a porous plug to analyze the temperature fluctuations and the factors influencing them, such as convection, compression, and expansion.", "scientific_discipline": "Physics", "scientific_subdiscipline": "Thermodynamics & Fluid Mechanics"}