{"article_id": "108561", "revised_title": "A Reassessment of the Lunar Theory and Eclipses of Agathocles and Thales", "topics": ["Lunar Theory", "Eclipse Prediction", "Astronomical History", "Lunar Tables", "Eclipses in Ancient History"], "tldr": "The author examines the historical accounts of eclipses involving Agathocles and Thales, and reevaluates the lunar tables and calculations used to predict these events. The study suggests that the eclipse of Agathocles should be considered the key eclipse for chronology and lunar astronomy, rather than the eclipse of Thales.", "scientific_discipline": "Astronomy", "scientific_subdiscipline": "Astrohistory & Astronomical Observations"}