{"article_id": "108547", "revised_title": "Geometrical Properties of Elliptic Integrals and Hyperconic Sections", "topics": ["Elliptic Integrals", "Geometry", "Hyperconic Sections", "Spherical Conic Sections", "Elliptic Functions"], "tldr": "The author investigates the geometrical properties of elliptic integrals and their relationship to hyperconic sections, discovering that they represent the intersections of surfaces of the second order. He introduces the concept of hyperconic sections and demonstrates their connection to various mathematical functions, including circular, logarithmic, and exponential functions.", "scientific_discipline": "Mathematics & Statistics", "scientific_subdiscipline": "Geometry & Topology"}