{"article_id": "108808", "revised_title": "Investigating the Sun's Magnetic Action on Earth", "topics": ["Magnetosphere", "Magnetic Field", "Solar Influence on Earth's Magnetism", "Magnetic Variations", "Magnetic Declination"], "tldr": "The author examines the nature of the sun's magnetic action on Earth, exploring the possibility of the sun acting as a great magnet and its effects on the Earth's magnetic field. The study concludes that the sun's magnetic influence alone cannot fully explain the observed diurnal variations in Earth's magnetism.", "scientific_discipline": "Environmental & Earth Sciences", "scientific_subdiscipline": "Magnetosphere & Geomagnetism"}