{"article_id": "109893", "revised_title": "Geographical Analysis of the North-Eastern Asia and the Contiguity of Asia and America", "topics": ["Geography", "Asia", "America", "Continental Connections", "Exploration"], "tldr": "Captain James Burney examines the geographical evidence surrounding the connection between Asia and America. He discusses various explorations and observations, including those of Captain Cook and Commodore Billings, and concludes that Asia and America are part of the same continent.", "scientific_discipline": "Environmental & Earth Sciences", "scientific_subdiscipline": "Geography & Cartography"}