{"article_id": "110116", "revised_title": "The Nervous Circle Connecting Voluntary Muscles with the Brain", "topics": ["Neuroscience", "Muscle Physiology", "Nerve Injury", "Sensory Nerves", "Motor Nerves"], "tldr": "Charles Bell investigates the nervous circle connecting voluntary muscles with the brain, demonstrating that two nerves with different properties are required for each muscle. He also explains the importance of this circle for conveying information about muscle state to the brain and maintaining muscle regulation.", "scientific_discipline": "Biology & Life Sciences", "scientific_subdiscipline": "Neuroscience & Neurophysiology"}