{"article_id": "110904", "revised_title": "Address Delivered before the Royal Society: Anniversary Meeting and Scientific Updates", "topics": ["Royal Society", "Treasurer Resignation", "Magnetic Observations", "Scientific Congress", "Scientific Experiments and Discoveries"], "tldr": "The Marquis of Northampton, President of the Royal Society, addresses the Anniversary Meeting, discussing the resignation of Sir John Lubbock as Treasurer, updates on magnetic observations, and the scientific congress held at Cambridge. He also mentions the successful return of the vessel sent to complete the magnetic survey of the southern hemisphere and the upcoming Arctic expedition led by Sir John Franklin.", "scientific_discipline": "Earth Sciences", "scientific_subdiscipline": "Geophysics & Geomagnetism"}