{"article_id": "111346", "revised_title": "On the Equation of Laplace's Functions and Coefficients", "topics": ["Mathematical Analysis", "Partial Differential Equations", "Laplace Transforms", "Mathematical Physics", "Applied Mathematics"], "tldr": "The author investigates Laplace's equation and its functions, providing a general solution for the equation and discussing the properties of Laplace's coefficients. The author also compares their results with those obtained by Professor Boole and demonstrates the applicability of the solution to various cases.", "scientific_discipline": "Mathematics & Statistics", "scientific_subdiscipline": "Analysis & Differential Equations"}