{"article_id": "111579", "revised_title": "On the Comparison of Hyperbolic Arcs and Elliptic Integrals", "topics": ["Elliptic Functions", "Hyperbolic Geometry", "Elliptic Integrals", "Algebraic Transformations", "Comparison of Arcs"], "tldr": "The author explores the comparison of hyperbolic arcs and elliptic integrals, finding a formula for the comparison of hyperbolic arcs and reducing the elliptic integral of the third kind to a form involving two variables.", "scientific_discipline": "Mathematics & Statistics", "scientific_subdiscipline": "Geometry & Algebra"}