{"article_id": "rspa_1907_0018", "revised_title": "Investigations on the Dark Space in Vacuum Tubes", "topics": ["Vacuum Physics", "Electron Theory", "Electrical Discharge", "Dark Space Phenomenon", "Electron Emission"], "tldr": "The author examines the dark space in vacuum tubes and its relation to the mean free path of electrons and the distribution of positive and negative charges. The experiments reveal that the size of the dark space varies with the degree of exhaustion and that the size of the enclosing tube does not influence the size of the dark space.", "scientific_discipline": "Physics", "scientific_subdiscipline": "Electrical & Optical Physics"}