{"article_id": "rspb_1918_0017", "revised_title": "The Physiological Basis of Thirst and its Relation to Water Intake", "topics": ["Thirst", "Water Intake", "Physiological Processes", "Hydration", "Desert Survival"], "tldr": "The author discusses the importance of water in physiological processes and how the sensation of thirst serves as a crucial mechanism to maintain the body's water balance. Thirst is an essential factor in survival, especially in extreme conditions like desert environments, where water intake is critical for maintaining life.", "scientific_discipline": "Biology & Life Sciences", "scientific_subdiscipline": "Physiology & Homeostasis"}