{"article_id": "rspb_1916_0014", "revised_title": "A New Approach to Color Vision Theory", "topics": ["Color Vision", "Optics", "Neuroscience", "Visual Perception", "Physiology of Vision"], "tldr": "The authors propose a new theory of color vision, suggesting that the perception of color is influenced by the interaction between light wavelengths and the physical properties of the eye's components. They argue that this theory can explain previously observed phenomena related to color perception and provide a more comprehensive understanding of the underlying mechanisms.", "scientific_discipline": "Biology & Life Sciences", "scientific_subdiscipline": "Neuroscience & Sensory Systems"}