{"article_id": "rspl_1887_0074", "revised_title": "Investigations on Rabies and Tubercular Swellings on Vicia Faba Roots", "topics": ["Rabies", "Virology", "Neurology", "Immunology", "Plant Pathology"], "tldr": "The authors investigate the virus of rabies and its effects on animals, finding that it resides in the cerebrospinal substance and peripheral nerves. They also study tubercular swellings on Vicia Faba roots, discovering that they contain a fungus and are infected by root hairs.", "scientific_discipline": "Biology & Life Sciences", "scientific_subdiscipline": "Microbiology & Virology"}