{"article_id": "rspl_1898_0037", "revised_title": "Crystal Structure Analysis of Metals in the Cubic System", "topics": ["Crystallography", "Cubic System", "Metallic Crystals", "Atomic Structure", "Crystal Packing"], "tldr": "The author investigates the intimate structure of crystals in the cubic system, focusing on metals with cubic cleavage. They analyze the atomic structure and packing of various metals, including palladium's ability to absorb hydrogen, providing insights into the open packing arrangement of metals in the cubic system.", "scientific_discipline": "Chemistry", "scientific_subdiscipline": "Materials Science & Crystallography"}