{"article_id": "rspl_1903_0014", "revised_title": "A Method for Measuring Tissue Fluid in Humans", "topics": ["Blood Circulation", "Tissue Fluid", "Blood Analysis", "Blood Pressure", "Lymphatic System"], "tldr": "The authors describe a method to measure tissue fluid in humans using a rubber ring to compress blood vessels and disperse lymph, allowing for the study of circulation and the effects of food on tissue fluid levels.", "scientific_discipline": "Medicine & Health Sciences", "scientific_subdiscipline": "Physiology & Pathophysiology"}