{"article_id": "rspl_1887_0008", "revised_title": "Improved Calculation of Napierian Logarithms and the Modulus of Common Logarithms", "topics": ["Mathematical Analysis", "Numerical Approximation", "Logarithms", "Error Correction", "Decimals"], "tldr": "The author revises and improves the calculation of Napierian logarithms and the modulus of common logarithms, correcting errors in previous calculations and extending the computations to more decimal places for greater accuracy.", "scientific_discipline": "Mathematics & Statistics", "scientific_subdiscipline": "Numerical Analysis & Approximation"}