{"article_id": "rspl_1873_0081", "revised_title": "On the Centre of Motion in the Human Eye: A Reevaluation of Donders' Theory", "topics": ["Eye Anatomy", "Optometry", "Ophthalmology", "Visual Perception", "Eye Movement"], "tldr": "The author challenges the existing theory of the eye's center of motion proposed by Donders and provides evidence that the center of motion is approximately one inch behind the cornea's anterior surface, outside the cornea's axis, and in the visual line.", "scientific_discipline": "Biology & Life Sciences", "scientific_subdiscipline": "Neurobiology & Sensory Systems"}