{"article_id": "rsta_1900_0001", "revised_title": "Recovery of Iron from Overstrain: Effects of Temperature, Mechanical Vibration, and Magnetic Agitation", "topics": ["Iron Hardening", "Overstrain Recovery", "Hysteresis in Materials", "Elasticity and Plasticity", "Mechanical Properties of Materials"], "tldr": "This study investigates the recovery of iron from overstrain through the effects of temperature, mechanical vibration, and magnetic agitation. The research explores the phenomenon of hysteresis in the relation of extension to stress in overstrained iron and demonstrates the recovery process using compression tests.", "scientific_discipline": "Engineering & Technology", "scientific_subdiscipline": "Materials Science & Engineering"}