{"article_id": "rsta_1887_0010", "revised_title": "On Hamilton's Numbers and their Asymptotic Properties", "topics": ["Algebraic Geometry", "Number Theory", "Hamiltonian Numbers", "Asymptotic Analysis", "Mathematical Reduction"], "tldr": "The authors discuss Hamilton's numbers, a sequence of numbers related to the reduction of polynomial equations, and explore their asymptotic properties. They also present a new formula for calculating these numbers and demonstrate how they can be used to derive other mathematical relationships.", "scientific_discipline": "Mathematics & Statistics", "scientific_subdiscipline": "Algebra & Number Theory"}