{"article_id": "rsta_1909_0006", "revised_title": "The Emission and Transmission of R\u00f6ntgen Rays: A Study of the Relation between Atomic Weight and Radiation Intensity", "topics": ["R\u00f6ntgen Rays", "Atomic Weight", "Ionization", "Selective Absorption", "Radiation Intensity"], "tldr": "This study investigates the relationship between atomic weight and the intensity of emitted and transmitted R\u00f6ntgen rays using an ionization method. The authors found that heavier metals produce more intense R\u00f6ntgen rays and that there is a correlation between atomic weight and radiation intensity.", "scientific_discipline": "Physics", "scientific_subdiscipline": "Atomic & Nuclear Physics"}