{"article_id": "rstl_1880_0021", "revised_title": "A Memoir on the Single and Double Theta-Functions and their Applications", "topics": ["Theta Functions", "Elliptic Functions", "Quotien", "Differential Equations", "Mathematical Analysis"], "tldr": "The author explores the properties of single and double theta-functions, elliptic functions, and quotient-functions, providing formulas and equations for their applications in mathematical analysis and differential equations.", "scientific_discipline": "Mathematics & Statistics", "scientific_subdiscipline": "Analysis & Calculus"}